allowedsites.py
django_dynamic_allowedsites-0.2.0.dist-info/LICENSE
django_dynamic_allowedsites-0.2.0.dist-info/METADATA
django_dynamic_allowedsites-0.2.0.dist-info/WHEEL
django_dynamic_allowedsites-0.2.0.dist-info/top_level.txt
django_dynamic_allowedsites-0.2.0.dist-info/RECORD
