Metadata-Version: 2.1
Name: django-dynamic-allowedsites
Version: 0.2.0
Summary: Dynamic ALLOWED_HOSTS based on the configured django.contrib.sites
Home-page: https://github.com/frankyjquintero/django-allowedsites
Author: Keryn Knight && nanuxbe && frankyjquintero
Author-email: python-package@kerynknight.com
License: BSD License
Platform: UNKNOWN
Classifier: Development Status :: 4 - Beta
Classifier: Intended Audience :: Developers
Classifier: License :: OSI Approved :: BSD License
Classifier: Framework :: Django
Classifier: Natural Language :: English
Classifier: Environment :: Web Environment
Classifier: Topic :: Internet :: WWW/HTTP
Classifier: Programming Language :: Python :: 2
Classifier: Programming Language :: Python :: 2.6
Classifier: Programming Language :: Python :: 2.7
Classifier: Programming Language :: Python :: 3
Classifier: Programming Language :: Python :: 3.3
Classifier: Programming Language :: Python :: 3.4
Classifier: Programming Language :: Python :: 3.5
Classifier: Programming Language :: Python :: 3.6
Classifier: Programming Language :: Python :: 3.7
Classifier: Programming Language :: Python :: 3.8
Requires-Dist: Django (>=1.4)
